idp_engine/Annotate.py
idp_engine/Assignments.py
idp_engine/Definition.py
idp_engine/EN.py
idp_engine/Expression.py
idp_engine/IDP_Z3.py
idp_engine/Idp.tx
idp_engine/Idp_to_Z3.py
idp_engine/Interpret.py
idp_engine/Parse.py
idp_engine/Propagate.py
idp_engine/Relevance.py
idp_engine/Run.py
idp_engine/Simplify.py
idp_engine/SymbolicPropagate.py
idp_engine/Theory.py
idp_engine/WDF.py
idp_engine/Z3_to_IDP.py
idp_engine/__init__.py
idp_engine/utils.py
idp_engine-0.12.0.dist-info/LICENSE.md
idp_engine-0.12.0.dist-info/METADATA
idp_engine-0.12.0.dist-info/WHEEL
idp_engine-0.12.0.dist-info/entry_points.txt
idp_engine-0.12.0.dist-info/RECORD
