Metadata-Version: 2.1
Name: idp-engine
Version: 0.12.0
Summary: IDP-Z3 is a reasoning engine for knowledge represented using the FO(.) (aka FO-dot) language.
Home-page: https://www.idp-z3.be
License: GNU LGPL 3
Author: pierre.carbonnelle
Author-email: pierre.carbonnelle@cs.kuleuven.be
Requires-Python: >=3.9,<3.14
Classifier: License :: Other/Proprietary License
Classifier: Programming Language :: Python :: 3
Classifier: Programming Language :: Python :: 3.9
Classifier: Programming Language :: Python :: 3.10
Classifier: Programming Language :: Python :: 3.11
Classifier: Programming Language :: Python :: 3.12
Classifier: Programming Language :: Python :: 3.13
Provides-Extra: benchmark-table
Requires-Dist: python-dateutil (>=2.8.2,<3.0.0)
Requires-Dist: restrictedpython (>=8.0,<9.0)
Requires-Dist: setuptools (>=70.0.0,<71.0.0)
Requires-Dist: textX (>=2.1.0,<3.0.0)
Requires-Dist: z3-solver (==4.11.2.0)
Project-URL: Documentation, https://docs.idp-z3.be
Project-URL: Repository, https://gitlab.com/krr/IDP-Z3
